meson-1.8.5.data/data/share/man/man1/meson.1
meson-1.8.5.data/data/share/polkit-1/actions/com.mesonbuild.install.policy
meson-1.8.5.dist-info/licenses/COPYING
mesonbuild/__init__.py
mesonbuild/_pathlib.py
mesonbuild/_typing.py
mesonbuild/arglist.py
mesonbuild/build.py
mesonbuild/coredata.py
mesonbuild/depfile.py
mesonbuild/envconfig.py
mesonbuild/environment.py
mesonbuild/machinefile.py
mesonbuild/mcompile.py
mesonbuild/mconf.py
mesonbuild/mdevenv.py
mesonbuild/mdist.py
mesonbuild/mesondata.py
mesonbuild/mesonlib.py
mesonbuild/mesonmain.py
mesonbuild/mformat.py
mesonbuild/minit.py
mesonbuild/minstall.py
mesonbuild/mintro.py
mesonbuild/mlog.py
mesonbuild/mparser.py
mesonbuild/msetup.py
mesonbuild/msubprojects.py
mesonbuild/mtest.py
mesonbuild/munstable_coredata.py
mesonbuild/optinterpreter.py
mesonbuild/options.py
mesonbuild/programs.py
mesonbuild/rewriter.py
mesonbuild/ast/__init__.py
mesonbuild/ast/interpreter.py
mesonbuild/ast/introspection.py
mesonbuild/ast/postprocess.py
mesonbuild/ast/printer.py
mesonbuild/ast/visitor.py
mesonbuild/backend/__init__.py
mesonbuild/backend/backends.py
mesonbuild/backend/ninjabackend.py
mesonbuild/backend/nonebackend.py
mesonbuild/backend/vs2010backend.py
mesonbuild/backend/vs2012backend.py
mesonbuild/backend/vs2013backend.py
mesonbuild/backend/vs2015backend.py
mesonbuild/backend/vs2017backend.py
mesonbuild/backend/vs2019backend.py
mesonbuild/backend/vs2022backend.py
mesonbuild/backend/xcodebackend.py
mesonbuild/cargo/__init__.py
mesonbuild/cargo/builder.py
mesonbuild/cargo/cfg.py
mesonbuild/cargo/interpreter.py
mesonbuild/cargo/manifest.py
mesonbuild/cargo/version.py
mesonbuild/cmake/__init__.py
mesonbuild/cmake/common.py
mesonbuild/cmake/executor.py
mesonbuild/cmake/fileapi.py
mesonbuild/cmake/generator.py
mesonbuild/cmake/interpreter.py
mesonbuild/cmake/toolchain.py
mesonbuild/cmake/traceparser.py
mesonbuild/cmake/tracetargets.py
mesonbuild/cmake/data/__init__.py
mesonbuild/cmake/data/preload.cmake
mesonbuild/compilers/__init__.py
mesonbuild/compilers/asm.py
meson-1.8.5.dist-info/METADATA
meson-1.8.5.dist-info/WHEEL
meson-1.8.5.dist-info/entry_points.txt
meson-1.8.5.dist-info/top_level.txt
meson-1.8.5.dist-info/RECORD
